thelookingglass/__init__.py
thelookingglass/application/__init__.py
thelookingglass/application/application_test.py
thelookingglass/infrastructure/__init__.py
thelookingglass/infrastructure/application_test.py
thelookingglass/ui/__init__.py
thelookingglass/ui/cli/__init__.py
thelookingglass/ui/http/__init__.py
thelookingglass-0.0.1.dist-info/LICENSE
thelookingglass-0.0.1.dist-info/METADATA
thelookingglass-0.0.1.dist-info/WHEEL
thelookingglass-0.0.1.dist-info/RECORD
