Metadata-Version: 2.1
Name: thelookingglass
Version: 0.0.1
Summary: 
License: The Unlicence
Author: Luís Miranda
Author-email: luistm@gmail.com
Requires-Python: >=3.10,<4.0
Classifier: License :: Other/Proprietary License
Classifier: Programming Language :: Python :: 3
Classifier: Programming Language :: Python :: 3.10
Classifier: Programming Language :: Python :: 3.11
